pdfflow/__init__.py
pdfflow/alphas_functions.py
pdfflow/alphas_interpolations.py
pdfflow/alphas_region_interpolator.py
pdfflow/configflow.py
pdfflow/functions.py
pdfflow/interpolations.py
pdfflow/neighbour_knots.py
pdfflow/pflow.py
pdfflow/region_interpolator.py
pdfflow/subgrid.py
pdfflow/tests/__init__.py
pdfflow/tests/test_alphas.py
pdfflow/tests/test_config.py
pdfflow/tests/test_lhapdf.py
pdfflow/tests/test_pflow.py
pdfflow-1.2.2.dist-info/LICENSE
pdfflow-1.2.2.dist-info/METADATA
pdfflow-1.2.2.dist-info/WHEEL
pdfflow-1.2.2.dist-info/top_level.txt
pdfflow-1.2.2.dist-info/RECORD
