Metadata-Version: 2.1
Name: pdfflow
Version: 1.2.2
Summary: PDF interpolation with Tensorflow
Home-page: https://github.com/N3PDF/pdfflow
Author: S.Carrazza, J.Cruz-Martinez, M.Rossi
Author-email: stefano.carrazza@cern.ch, juan.cruz@mi.infn.it, marco.rossi5@unimi.it
Classifier: Operating System :: Unix
Classifier: Programming Language :: Python
Classifier: Programming Language :: Python :: 3
Classifier: Topic :: Scientific/Engineering
Classifier: Topic :: Scientific/Engineering :: Physics
Requires-Python: >=3.6
License-File: LICENSE
Requires-Dist: numpy >=1.21
Requires-Dist: pyyaml
Requires-Dist: lhapdf-management
Provides-Extra: capi
Requires-Dist: cffi ; extra == 'capi'
Provides-Extra: docs
Requires-Dist: sphinx-rtd-theme ; extra == 'docs'
Requires-Dist: recommonmark ; extra == 'docs'
Requires-Dist: sphinxcontrib-bibtex ; extra == 'docs'
Provides-Extra: examples
Requires-Dist: matplotlib ; extra == 'examples'
Requires-Dist: vegasflow ; extra == 'examples'
Provides-Extra: tf
Requires-Dist: tensorflow ; extra == 'tf'
Provides-Extra: tf-amd
Requires-Dist: tensorflow-rocm ; extra == 'tf-amd'
Provides-Extra: tf-cpu
Requires-Dist: tensorflow-cpu ; extra == 'tf-cpu'
Provides-Extra: tf-gpu
Requires-Dist: tensorflow-gpu ; extra == 'tf-gpu'
